st_tschart/__init__.py
st_tschart/__pycache__/__init__.cpython-313.pyc
st_tschart/frontend/build/index.css
st_tschart/frontend/build/index.html
st_tschart/frontend/build/index.js
st_tschart-0.1.0.dist-info/licenses/LICENSE
st_tschart-0.1.0.dist-info/METADATA
st_tschart-0.1.0.dist-info/WHEEL
st_tschart-0.1.0.dist-info/top_level.txt
st_tschart-0.1.0.dist-info/RECORD
