Metadata-Version: 2.4
Name: st-tschart
Version: 0.1.0
Summary: A Streamlit component for rendering interactive timeseries charts with CDF integration
Author-email: Everton Colling <evertoncolling@gmail.com>
License: MIT
Project-URL: Homepage, https://github.com/evertoncolling/st-tschart
Project-URL: Repository, https://github.com/evertoncolling/st-tschart
Project-URL: Issues, https://github.com/evertoncolling/st-tschart/issues
Keywords: streamlit,timeseries,chart,visualization,component,cognite,cdf
Classifier: Development Status :: 3 - Alpha
Classifier: Intended Audience :: Developers
Classifier: Programming Language :: Python :: 3
Classifier: Programming Language :: Python :: 3.9
Classifier: Programming Language :: Python :: 3.10
Classifier: Programming Language :: Python :: 3.11
Classifier: Programming Language :: Python :: 3.12
Classifier: Topic :: Software Development :: Libraries :: Python Modules
Requires-Python: >=3.13
License-File: LICENSE
Requires-Dist: streamlit>=1.28.0
Dynamic: license-file
